speechmark/__init__.py
speechmark/__main__.py
speechmark/speechmark.py
speechmark/test/__init__.py
speechmark/test/test_speechmark.py
speechmark-0.10.0.dist-info/LICENSE
speechmark-0.10.0.dist-info/METADATA
speechmark-0.10.0.dist-info/WHEEL
speechmark-0.10.0.dist-info/top_level.txt
speechmark-0.10.0.dist-info/RECORD
