Metadata-Version: 2.1
Name: speechmark
Version: 0.10.0
Summary: A markup language for Speech and Dialogue.
Author-email: Tundish <tundish@gigeconomy.org.uk>
Maintainer-email: Tundish <tundish@gigeconomy.org.uk>
License: GNU LESSER GENERAL PUBLIC LICENSE
Keywords: markup
Classifier: Development Status :: 4 - Beta
Classifier: Programming Language :: Python
Requires-Python: >=3.10
License-File: LICENSE
Requires-Dist: tomli (>=2.0.0) ; python_version < "3.11"
